Workbook

Sheet Dashboard
B2: E-COMMERCE SALES & CUSTOMER ANALYTICS DASHBOARD
B4: KPI | C4: Value
B5: Total Orders | C5: =COUNTA(Orders!A2:A8001) -> 8000
B6: Total Customers | C6: =COUNTA(Customers!A2:A601) -> 600
B7: Gross Revenue | C7: =SUMIFS(Orders!H2:H8001,Orders!E2:E8001,"Delivered")+SUMIFS(Orders!H2:H8001,Orders!E2:E8001,"Returned") -> 44691407
B8: Total Refunds | C8: =SUM(Returns!H2:H884) -> 2289755.4
B9: Return Count | C9: =COUNTA(Returns!A2:A884) -> 883
B10: Revenue-Generating Orders | C10: =COUNTIFS(Orders!E2:E8001,"Delivered")+COUNTIFS(Orders!E2:E8001,"Returned") -> 7429
B11: Avg Order Value | C11: =C7/C10 -> 6015.8039
B12: Refunds as % of Revenue | C12: =C8/C7 -> 0.051234802
B13: Return Rate % | C13: =C9/C5 -> 0.110375
B15: See tabs: Revenue_Trend, Category_Performance, Customer_Segments, Returns_Analysis for detailed breakdowns and charts.

Sheet Revenue_Trend
A1: Monthly Revenue & Order Trend
A3: Month | B3: Total Orders | C3: Total Revenue | D3: Avg Order Value | E3: MoM Growth %
A4: 2024-01 | B4: =SUMPRODUCT((LEFT(Orders!$C$2:$C$8001,7)=A4)*((Orders!$E$2:$E$8001="Delivered")+(Orders!$E$2:$E$8001="Returned"))) -> 105 | C4: =SUMPRODUCT((LEFT(Orders!$C$2:$C$8001,7)=A4)*((Orders!$E$2:$E$8001="Delivered")+(Orders!$E$2:$E$8001="Returned"))*Orders!$H$2:$H$8001) -> 661374.81 | D4: =IFERROR(C4/B4,0) -> 6298.8077 | E4: 0
A5: 2024-02 | B5: =SUMPRODUCT((LEFT(Orders!$C$2:$C$8001,7)=A5)*((Orders!$E$2:$E$8001="Delivered")+(Orders!$E$2:$E$8001="Returned"))) -> 119 | C5: =SUMPRODUCT((LEFT(Orders!$C$2:$C$8001,7)=A5)*((Orders!$E$2:$E$8001="Delivered")+(Orders!$E$2:$E$8001="Returned"))*Orders!$H$2:$H$8001) -> 581726.28 | D5: =IFERROR(C5/B5,0) -> 4888.4561 | E5: =IFERROR((C5-C4)/C4,0) -> -0.12042873
A6: 2024-03 | B6: =SUMPRODUCT((LEFT(Orders!$C$2:$C$8001,7)=A6)*((Orders!$E$2:$E$8001="Delivered")+(Orders!$E$2:$E$8001="Returned"))) -> 129 | C6: =SUMPRODUCT((LEFT(Orders!$C$2:$C$8001,7)=A6)*((Orders!$E$2:$E$8001="Delivered")+(Orders!$E$2:$E$8001="Returned"))*Orders!$H$2:$H$8001) -> 745999.33 | D6: =IFERROR(C6/B6,0) -> 5782.9405 | E6: =IFERROR((C6-C5)/C5,0) -> 0.28238891
A7: 2024-04 | B7: =SUMPRODUCT((LEFT(Orders!$C$2:$C$8001,7)=A7)*((Orders!$E$2:$E$8001="Delivered")+(Orders!$E$2:$E$8001="Returned"))) -> 143 | C7: =SUMPRODUCT((LEFT(Orders!$C$2:$C$8001,7)=A7)*((Orders!$E$2:$E$8001="Delivered")+(Orders!$E$2:$E$8001="Returned"))*Orders!$H$2:$H$8001) -> 821243.77 | D7: =IFERROR(C7/B7,0) -> 5742.9634 | E7: =IFERROR((C7-C6)/C6,0) -> 0.10086395
A8: 2024-05 | B8: =SUMPRODUCT((LEFT(Orders!$C$2:$C$8001,7)=A8)*((Orders!$E$2:$E$8001="Delivered")+(Orders!$E$2:$E$8001="Returned"))) -> 112 | C8: =SUMPRODUCT((LEFT(Orders!$C$2:$C$8001,7)=A8)*((Orders!$E$2:$E$8001="Delivered")+(Orders!$E$2:$E$8001="Returned"))*Orders!$H$2:$H$8001) -> 601815.68 | D8: =IFERROR(C8/B8,0) -> 5373.3543 | E8: =IFERROR((C8-C7)/C7,0) -> -0.26718996
A9: 2024-06 | B9: =SUMPRODUCT((LEFT(Orders!$C$2:$C$8001,7)=A9)*((Orders!$E$2:$E$8001="Delivered")+(Orders!$E$2:$E$8001="Returned"))) -> 207 | C9: =SUMPRODUCT((LEFT(Orders!$C$2:$C$8001,7)=A9)*((Orders!$E$2:$E$8001="Delivered")+(Orders!$E$2:$E$8001="Returned"))*Orders!$H$2:$H$8001) -> 1170430.6 | D9: =IFERROR(C9/B9,0) -> 5654.2542 | E9: =IFERROR((C9-C8)/C8,0) -> 0.94483238
A10: 2024-07 | B10: =SUMPRODUCT((LEFT(Orders!$C$2:$C$8001,7)=A10)*((Orders!$E$2:$E$8001="Delivered")+(Orders!$E$2:$E$8001="Returned"))) -> 223 | C10: =SUMPRODUCT((LEFT(Orders!$C$2:$C$8001,7)=A10)*((Orders!$E$2:$E$8001="Delivered")+(Orders!$E$2:$E$8001="Returned"))*Orders!$H$2:$H$8001) -> 1329627.7 | D10: =IFERROR(C10/B10,0) -> 5962.4559 | E10: =IFERROR((C10-C9)/C9,0) -> 0.13601579
A11: 2024-08 | B11: =SUMPRODUCT((LEFT(Orders!$C$2:$C$8001,7)=A11)*((Orders!$E$2:$E$8001="Delivered")+(Orders!$E$2:$E$8001="Returned"))) -> 183 | C11: =SUMPRODUCT((LEFT(Orders!$C$2:$C$8001,7)=A11)*((Orders!$E$2:$E$8001="Delivered")+(Orders!$E$2:$E$8001="Returned"))*Orders!$H$2:$H$8001) -> 1024287.4 | D11: =IFERROR(C11/B11,0) -> 5597.1992 | E11: =IFERROR((C11-C10)/C10,0) -> -0.2296434
A12: 2024-09 | B12: =SUMPRODUCT((LEFT(Orders!$C$2:$C$8001,7)=A12)*((Orders!$E$2:$E$8001="Delivered")+(Orders!$E$2:$E$8001="Returned"))) -> 203 | C12: =SUMPRODUCT((LEFT(Orders!$C$2:$C$8001,7)=A12)*((Orders!$E$2:$E$8001="Delivered")+(Orders!$E$2:$E$8001="Returned"))*Orders!$H$2:$H$8001) -> 1296327.1 | D12: =IFERROR(C12/B12,0) -> 6385.848 | E12: =IFERROR((C12-C11)/C11,0) -> 0.26558922
A13: 2024-10 | B13: =SUMPRODUCT((LEFT(Orders!$C$2:$C$8001,7)=A13)*((Orders!$E$2:$E$8001="Delivered")+(Orders!$E$2:$E$8001="Returned"))) -> 333 | C13: =SUMPRODUCT((LEFT(Orders!$C$2:$C$8001,7)=A13)*((Orders!$E$2:$E$8001="Delivered")+(Orders!$E$2:$E$8001="Returned"))*Orders!$H$2:$H$8001) -> 1999628.6 | D13: =IFERROR(C13/B13,0) -> 6004.8908 | E13: =IFERROR((C13-C12)/C12,0) -> 0.54253396
A14: 2024-11 | B14: =SUMPRODUCT((LEFT(Orders!$C$2:$C$8001,7)=A14)*((Orders!$E$2:$E$8001="Delivered")+(Orders!$E$2:$E$8001="Returned"))) -> 438 | C14: =SUMPRODUCT((LEFT(Orders!$C$2:$C$8001,7)=A14)*((Orders!$E$2:$E$8001="Delivered")+(Orders!$E$2:$E$8001="Returned"))*Orders!$H$2:$H$8001) -> 2577631.2 | D14: =IFERROR(C14/B14,0) -> 5885.0027 | E14: =IFERROR((C14-C13)/C13,0) -> 0.28905494
A15: 2024-12 | B15: =SUMPRODUCT((LEFT(Orders!$C$2:$C$8001,7)=A15)*((Orders!$E$2:$E$8001="Delivered")+(Orders!$E$2:$E$8001="Returned"))) -> 417 | C15: =SUMPRODUCT((LEFT(Orders!$C$2:$C$8001,7)=A15)*((Orders!$E$2:$E$8001="Delivered")+(Orders!$E$2:$E$8001="Returned"))*Orders!$H$2:$H$8001) -> 2474712.2 | D15: =IFERROR(C15/B15,0) -> 5934.5616 | E15: =IFERROR((C15-C14)/C14,0) -> -0.039927752
A16: 2025-01 | B16: =SUMPRODUCT((LEFT(Orders!$C$2:$C$8001,7)=A16)*((Orders!$E$2:$E$8001="Delivered")+(Orders!$E$2:$E$8001="Returned"))) -> 260 | C16: =SUMPRODUCT((LEFT(Orders!$C$2:$C$8001,7)=A16)*((Orders!$E$2:$E$8001="Delivered")+(Orders!$E$2:$E$8001="Returned"))*Orders!$H$2:$H$8001) -> 1674319.8 | D16: =IFERROR(C16/B16,0) -> 6439.6915 | E16: =IFERROR((C16-C15)/C15,0) -> -0.32342847
... A27: 2025-12 | B27: =SUMPRODUCT((LEFT(Orders!$C$2:$C$8001,7)=A27)*((Orders!$E$2:$E$8001="Delivered")+(Orders!$E$2:$E$8001="Returned"))) -> 488 | C27: =SUMPRODUCT((LEFT(Orders!$C$2:$C$8001,7)=A27)*((Orders!$E$2:$E$8001="Delivered")+(Orders!$E$2:$E$8001="Returned"))*Orders!$H$2:$H$8001) -> 3132208.7 | D27: =IFERROR(C27/B27,0) -> 6418.4605 | E27: =IFERROR((C27-C26)/C26,0) -> -0.12319551

Sheet Category_Performance
A1: Revenue & Return Performance by Category
A2: Note: Revenue here is product-level (line item) revenue and excludes shipping fees, so the total is slightly below Dashboard Gross Revenue.
A3: Category | B3: Units Sold | C3: Revenue | D3: % of Total Revenue | E3: Units Returned | F3: Return Rate %
A4: Beauty & Personal Care | B4: =SUMIFS(Order_Items!$D$2:$D$16419,Order_Items!$I$2:$I$16419,A4,Order_Items!$J$2:$J$16419,"Delivered")+SUMIFS(Order_Items!$D$2:$D$16419,Order_Items!$I$2:$I$16419,A4,Order_Items!$J$2:$J$16419,"Returned") -> 2744 | C4: =SUMIFS(Order_Items!$G$2:$G$16419,Order_Items!$I$2:$I$16419,A4,Order_Items!$J$2:$J$16419,"Delivered")+SUMIFS(Order_Items!$G$2:$G$16419,Order_Items!$I$2:$I$16419,A4,Order_Items!$J$2:$J$16419,"Returned") -> 3206216.7 | D4: =C4/SUM($C$4:$C$9) -> 0.072061755 | E4: =SUMPRODUCT((Returns!$D$2:$D$884<>"")*(IFERROR(INDEX(Products!$C$2:$C$51,MATCH(Returns!$D$2:$D$884,Products!$A$2:$A$51,0)),"")=A4)) -> 112 | F4: =IFERROR(E4/B4,0) -> 0.040816327
A5: Books & Stationery | B5: =SUMIFS(Order_Items!$D$2:$D$16419,Order_Items!$I$2:$I$16419,A5,Order_Items!$J$2:$J$16419,"Delivered")+SUMIFS(Order_Items!$D$2:$D$16419,Order_Items!$I$2:$I$16419,A5,Order_Items!$J$2:$J$16419,"Returned") -> 5092 | C5: =SUMIFS(Order_Items!$G$2:$G$16419,Order_Items!$I$2:$I$16419,A5,Order_Items!$J$2:$J$16419,"Delivered")+SUMIFS(Order_Items!$G$2:$G$16419,Order_Items!$I$2:$I$16419,A5,Order_Items!$J$2:$J$16419,"Returned") -> 2771586.3 | D5: =C5/SUM($C$4:$C$9) -> 0.062293161 | E5: =SUMPRODUCT((Returns!$D$2:$D$884<>"")*(IFERROR(INDEX(Products!$C$2:$C$51,MATCH(Returns!$D$2:$D$884,Products!$A$2:$A$51,0)),"")=A5)) -> 219 | F5: =IFERROR(E5/B5,0) -> 0.043008641
A6: Electronics | B6: =SUMIFS(Order_Items!$D$2:$D$16419,Order_Items!$I$2:$I$16419,A6,Order_Items!$J$2:$J$16419,"Delivered")+SUMIFS(Order_Items!$D$2:$D$16419,Order_Items!$I$2:$I$16419,A6,Order_Items!$J$2:$J$16419,"Returned") -> 3619 | C6: =SUMIFS(Order_Items!$G$2:$G$16419,Order_Items!$I$2:$I$16419,A6,Order_Items!$J$2:$J$16419,"Delivered")+SUMIFS(Order_Items!$G$2:$G$16419,Order_Items!$I$2:$I$16419,A6,Order_Items!$J$2:$J$16419,"Returned") -> 11477080 | D6: =C6/SUM($C$4:$C$9) -> 0.25795466 | E6: =SUMPRODUCT((Returns!$D$2:$D$884<>"")*(IFERROR(INDEX(Products!$C$2:$C$51,MATCH(Returns!$D$2:$D$884,Products!$A$2:$A$51,0)),"")=A6)) -> 161 | F6: =IFERROR(E6/B6,0) -> 0.044487427
A7: Fashion | B7: =SUMIFS(Order_Items!$D$2:$D$16419,Order_Items!$I$2:$I$16419,A7,Order_Items!$J$2:$J$16419,"Delivered")+SUMIFS(Order_Items!$D$2:$D$16419,Order_Items!$I$2:$I$16419,A7,Order_Items!$J$2:$J$16419,"Returned") -> 4142 | C7: =SUMIFS(Order_Items!$G$2:$G$16419,Order_Items!$I$2:$I$16419,A7,Order_Items!$J$2:$J$16419,"Delivered")+SUMIFS(Order_Items!$G$2:$G$16419,Order_Items!$I$2:$I$16419,A7,Order_Items!$J$2:$J$16419,"Returned") -> 10808177 | D7: =C7/SUM($C$4:$C$9) -> 0.24292063 | E7: =SUMPRODUCT((Returns!$D$2:$D$884<>"")*(IFERROR(INDEX(Products!$C$2:$C$51,MATCH(Returns!$D$2:$D$884,Products!$A$2:$A$51,0)),"")=A7)) -> 163 | F7: =IFERROR(E7/B7,0) -> 0.03935297
A8: Home & Kitchen | B8: =SUMIFS(Order_Items!$D$2:$D$16419,Order_Items!$I$2:$I$16419,A8,Order_Items!$J$2:$J$16419,"Delivered")+SUMIFS(Order_Items!$D$2:$D$16419,Order_Items!$I$2:$I$16419,A8,Order_Items!$J$2:$J$16419,"Returned") -> 2274 | C8: =SUMIFS(Order_Items!$G$2:$G$16419,Order_Items!$I$2:$I$16419,A8,Order_Items!$J$2:$J$16419,"Delivered")+SUMIFS(Order_Items!$G$2:$G$16419,Order_Items!$I$2:$I$16419,A8,Order_Items!$J$2:$J$16419,"Returned") -> 8380245.1 | D8: =C8/SUM($C$4:$C$9) -> 0.18835132 | E8: =SUMPRODUCT((Returns!$D$2:$D$884<>"")*(IFERROR(INDEX(Products!$C$2:$C$51,MATCH(Returns!$D$2:$D$884,Products!$A$2:$A$51,0)),"")=A8)) -> 98 | F8: =IFERROR(E8/B8,0) -> 0.043095866
A9: Sports & Fitness | B9: =SUMIFS(Order_Items!$D$2:$D$16419,Order_Items!$I$2:$I$16419,A9,Order_Items!$J$2:$J$16419,"Delivered")+SUMIFS(Order_Items!$D$2:$D$16419,Order_Items!$I$2:$I$16419,A9,Order_Items!$J$2:$J$16419,"Returned") -> 3229 | C9: =SUMIFS(Order_Items!$G$2:$G$16419,Order_Items!$I$2:$I$16419,A9,Order_Items!$J$2:$J$16419,"Delivered")+SUMIFS(Order_Items!$G$2:$G$16419,Order_Items!$I$2:$I$16419,A9,Order_Items!$J$2:$J$16419,"Returned") -> 7849320.7 | D9: =C9/SUM($C$4:$C$9) -> 0.17641846 | E9: =SUMPRODUCT((Returns!$D$2:$D$884<>"")*(IFERROR(INDEX(Products!$C$2:$C$51,MATCH(Returns!$D$2:$D$884,Products!$A$2:$A$51,0)),"")=A9)) -> 130 | F9: =IFERROR(E9/B9,0) -> 0.040260142

Sheet Customer_Segments
A1: Customer Purchasing Behavior — RFM Segmentation
A2: Recency = days since last order (lower = more recent). Frequency = number of orders. Monetary = total spend. | L2: Segment Summary
L3: Segment | M3: Customers
A4: Customer ID | B4: Name | C4: Frequency (Orders) | D4: Monetary (Revenue) | E4: Last Order Date | F4: Recency (Days) | G4: F Score | H4: M Score | I4: R Score | J4: Segment | L4: Champions | M4: =COUNTIF($J$5:$J$604,L4) -> 0
A5: =Customers!A2 -> CUST00001 | B5: =Customers!B2&" "&Customers!C2 -> Liam Nair | C5: =COUNTIFS(Orders!$B$2:$B$8001,A5,Orders!$E$2:$E$8001,"Delivered")+COUNTIFS(Orders!$B$2:$B$8001,A5,Orders!$E$2:$E$8001,"Returned") -> 4 | D5: =SUMIFS(Orders!$H$2:$H$8001,Orders!$B$2:$B$8001,A5,Orders!$E$2:$E$8001,"Delivered")+SUMIFS(Orders!$H$2:$H$8001,Orders!$B$2:$B$8001,A5,Orders!$E$2:$E$8001,"Returned") -> 21943.47 | E5: =IFERROR(maxifs(Orders!$C$2:$C$8001,Orders!$B$2:$B$8001,A5),"") | F5: =IF(E5="","",MAX(Orders!$C$2:$C$8001)-E5) | G5: =IFERROR(CEILING(percentrank.inc($C$5:$C$604,C5)*4,1),1) -> 1 | H5: =IFERROR(CEILING(percentrank.inc($D$5:$D$604,D5)*4,1),1) -> 1 | I5: =IF(F5="",1,IFERROR(5-CEILING(percentrank.inc($F$5:$F$604,F5)*4,1),1)) -> 1 | J5: =IF(AND(I5>=3,G5>=3,H5>=3),"Champions",IF(AND(I5>=3,G5<=2),"New / Promising",IF(AND(I5<=2,G5>=3,H5>=3),"At Risk (High Value)",IF(AND(I5<=2,G5<=2),"Lost / Dormant","Regular")))) -> Lost / Dormant | L5: New / Promising | M5: =COUNTIF($J$5:$J$604,L5) -> 0
A6: =Customers!A3 -> CUST00002 | B6: =Customers!B3&" "&Customers!C3 -> Lucas Ramirez | C6: =COUNTIFS(Orders!$B$2:$B$8001,A6,Orders!$E$2:$E$8001,"Delivered")+COUNTIFS(Orders!$B$2:$B$8001,A6,Orders!$E$2:$E$8001,"Returned") -> 13 | D6: =SUMIFS(Orders!$H$2:$H$8001,Orders!$B$2:$B$8001,A6,Orders!$E$2:$E$8001,"Delivered")+SUMIFS(Orders!$H$2:$H$8001,Orders!$B$2:$B$8001,A6,Orders!$E$2:$E$8001,"Returned") -> 92901.53 | E6: =IFERROR(maxifs(Orders!$C$2:$C$8001,Orders!$B$2:$B$8001,A6),"") | F6: =IF(E6="","",MAX(Orders!$C$2:$C$8001)-E6) | G6: =IFERROR(CEILING(percentrank.inc($C$5:$C$604,C6)*4,1),1) -> 1 | H6: =IFERROR(CEILING(percentrank.inc($D$5:$D$604,D6)*4,1),1) -> 1 | I6: =IF(F6="",1,IFERROR(5-CEILING(percentrank.inc($F$5:$F$604,F6)*4,1),1)) -> 1 | J6: =IF(AND(I6>=3,G6>=3,H6>=3),"Champions",IF(AND(I6>=3,G6<=2),"New / Promising",IF(AND(I6<=2,G6>=3,H6>=3),"At Risk (High Value)",IF(AND(I6<=2,G6<=2),"Lost / Dormant","Regular")))) -> Lost / Dormant | L6: At Risk (High Value) | M6: =COUNTIF($J$5:$J$604,L6) -> 0
A7: =Customers!A4 -> CUST00003 | B7: =Customers!B4&" "&Customers!C4 -> Elizabeth Young | C7: =COUNTIFS(Orders!$B$2:$B$8001,A7,Orders!$E$2:$E$8001,"Delivered")+COUNTIFS(Orders!$B$2:$B$8001,A7,Orders!$E$2:$E$8001,"Returned") -> 11 | D7: =SUMIFS(Orders!$H$2:$H$8001,Orders!$B$2:$B$8001,A7,Orders!$E$2:$E$8001,"Delivered")+SUMIFS(Orders!$H$2:$H$8001,Orders!$B$2:$B$8001,A7,Orders!$E$2:$E$8001,"Returned") -> 60865.38 | E7: =IFERROR(maxifs(Orders!$C$2:$C$8001,Orders!$B$2:$B$8001,A7),"") | F7: =IF(E7="","",MAX(Orders!$C$2:$C$8001)-E7) | G7: =IFERROR(CEILING(percentrank.inc($C$5:$C$604,C7)*4,1),1) -> 1 | H7: =IFERROR(CEILING(percentrank.inc($D$5:$D$604,D7)*4,1),1) -> 1 | I7: =IF(F7="",1,IFERROR(5-CEILING(percentrank.inc($F$5:$F$604,F7)*4,1),1)) -> 1 | J7: =IF(AND(I7>=3,G7>=3,H7>=3),"Champions",IF(AND(I7>=3,G7<=2),"New / Promising",IF(AND(I7<=2,G7>=3,H7>=3),"At Risk (High Value)",IF(AND(I7<=2,G7<=2),"Lost / Dormant","Regular")))) -> Lost / Dormant | L7: Lost / Dormant | M7: =COUNTIF($J$5:$J$604,L7) -> 600
A8: =Customers!A5 -> CUST00004 | B8: =Customers!B5&" "&Customers!C5 -> Kiara Perez | C8: =COUNTIFS(Orders!$B$2:$B$8001,A8,Orders!$E$2:$E$8001,"Delivered")+COUNTIFS(Orders!$B$2:$B$8001,A8,Orders!$E$2:$E$8001,"Returned") -> 6 | D8: =SUMIFS(Orders!$H$2:$H$8001,Orders!$B$2:$B$8001,A8,Orders!$E$2:$E$8001,"Delivered")+SUMIFS(Orders!$H$2:$H$8001,Orders!$B$2:$B$8001,A8,Orders!$E$2:$E$8001,"Returned") -> 35050.86 | E8: =IFERROR(maxifs(Orders!$C$2:$C$8001,Orders!$B$2:$B$8001,A8),"") | F8: =IF(E8="","",MAX(Orders!$C$2:$C$8001)-E8) | G8: =IFERROR(CEILING(percentrank.inc($C$5:$C$604,C8)*4,1),1) -> 1 | H8: =IFERROR(CEILING(percentrank.inc($D$5:$D$604,D8)*4,1),1) -> 1 | I8: =IF(F8="",1,IFERROR(5-CEILING(percentrank.inc($F$5:$F$604,F8)*4,1),1)) -> 1 | J8: =IF(AND(I8>=3,G8>=3,H8>=3),"Champions",IF(AND(I8>=3,G8<=2),"New / Promising",IF(AND(I8<=2,G8>=3,H8>=3),"At Risk (High Value)",IF(AND(I8<=2,G8<=2),"Lost / Dormant","Regular")))) -> Lost / Dormant | L8: Regular | M8: =COUNTIF($J$5:$J$604,L8) -> 0
A9: =Customers!A6 -> CUST00005 | B9: =Customers!B6&" "&Customers!C6 -> Ananya Lee | C9: =COUNTIFS(Orders!$B$2:$B$8001,A9,Orders!$E$2:$E$8001,"Delivered")+COUNTIFS(Orders!$B$2:$B$8001,A9,Orders!$E$2:$E$8001,"Returned") -> 13 | D9: =SUMIFS(Orders!$H$2:$H$8001,Orders!$B$2:$B$8001,A9,Orders!$E$2:$E$8001,"Delivered")+SUMIFS(Orders!$H$2:$H$8001,Orders!$B$2:$B$8001,A9,Orders!$E$2:$E$8001,"Returned") -> 88353.78 | E9: =IFERROR(maxifs(Orders!$C$2:$C$8001,Orders!$B$2:$B$8001,A9),"") | F9: =IF(E9="","",MAX(Orders!$C$2:$C$8001)-E9) | G9: =IFERROR(CEILING(percentrank.inc($C$5:$C$604,C9)*4,1),1) -> 1 | H9: =IFERROR(CEILING(percentrank.inc($D$5:$D$604,D9)*4,1),1) -> 1 | I9: =IF(F9="",1,IFERROR(5-CEILING(percentrank.inc($F$5:$F$604,F9)*4,1),1)) -> 1 | J9: =IF(AND(I9>=3,G9>=3,H9>=3),"Champions",IF(AND(I9>=3,G9<=2),"New / Promising",IF(AND(I9<=2,G9>=3,H9>=3),"At Risk (High Value)",IF(AND(I9<=2,G9<=2),"Lost / Dormant","Regular")))) -> Lost / Dormant
A10: =Customers!A7 -> CUST00006 | B10: =Customers!B7&" "&Customers!C7 -> William Reddy | C10: =COUNTIFS(Orders!$B$2:$B$8001,A10,Orders!$E$2:$E$8001,"Delivered")+COUNTIFS(Orders!$B$2:$B$8001,A10,Orders!$E$2:$E$8001,"Returned") -> 4 | D10: =SUMIFS(Orders!$H$2:$H$8001,Orders!$B$2:$B$8001,A10,Orders!$E$2:$E$8001,"Delivered")+SUMIFS(Orders!$H$2:$H$8001,Orders!$B$2:$B$8001,A10,Orders!$E$2:$E$8001,"Returned") -> 12842.41 | E10: =IFERROR(maxifs(Orders!$C$2:$C$8001,Orders!$B$2:$B$8001,A10),"") | F10: =IF(E10="","",MAX(Orders!$C$2:$C$8001)-E10) | G10: =IFERROR(CEILING(percentrank.inc($C$5:$C$604,C10)*4,1),1) -> 1 | H10: =IFERROR(CEILING(percentrank.inc($D$5:$D$604,D10)*4,1),1) -> 1 | I10: =IF(F10="",1,IFERROR(5-CEILING(percentrank.inc($F$5:$F$604,F10)*4,1),1)) -> 1 | J10: =IF(AND(I10>=3,G10>=3,H10>=3),"Champions",IF(AND(I10>=3,G10<=2),"New / Promising",IF(AND(I10<=2,G10>=3,H10>=3),"At Risk (High Value)",IF(AND(I10<=2,G10<=2),"Lost / Dormant","Regular")))) -> Lost / Dormant
A11: =Customers!A8 -> CUST00007 | B11: =Customers!B8&" "&Customers!C8 -> Susan Nair | C11: =COUNTIFS(Orders!$B$2:$B$8001,A11,Orders!$E$2:$E$8001,"Delivered")+COUNTIFS(Orders!$B$2:$B$8001,A11,Orders!$E$2:$E$8001,"Returned") -> 4 | D11: =SUMIFS(Orders!$H$2:$H$8001,Orders!$B$2:$B$8001,A11,Orders!$E$2:$E$8001,"Delivered")+SUMIFS(Orders!$H$2:$H$8001,Orders!$B$2:$B$8001,A11,Orders!$E$2:$E$8001,"Returned") -> 51053.36 | E11: =IFERROR(maxifs(Orders!$C$2:$C$8001,Orders!$B$2:$B$8001,A11),"") | F11: =IF(E11="","",MAX(Orders!$C$2:$C$8001)-E11) | G11: =IFERROR(CEILING(percentrank.inc($C$5:$C$604,C11)*4,1),1) -> 1 | H11: =IFERROR(CEILING(percentrank.inc($D$5:$D$604,D11)*4,1),1) -> 1 | I11: =IF(F11="",1,IFERROR(5-CEILING(percentrank.inc($F$5:$F$604,F11)*4,1),1)) -> 1 | J11: =IF(AND(I11>=3,G11>=3,H11>=3),"Champions",IF(AND(I11>=3,G11<=2),"New / Promising",IF(AND(I11<=2,G11>=3,H11>=3),"At Risk (High Value)",IF(AND(I11<=2,G11<=2),"Lost / Dormant","Regular")))) -> Lost / Dormant
A12: =Customers!A9 -> CUST00008 | B12: =Customers!B9&" "&Customers!C9 -> Sofia Thomas | C12: =COUNTIFS(Orders!$B$2:$B$8001,A12,Orders!$E$2:$E$8001,"Delivered")+COUNTIFS(Orders!$B$2:$B$8001,A12,Orders!$E$2:$E$8001,"Returned") -> 4 | D12: =SUMIFS(Orders!$H$2:$H$8001,Orders!$B$2:$B$8001,A12,Orders!$E$2:$E$8001,"Delivered")+SUMIFS(Orders!$H$2:$H$8001,Orders!$B$2:$B$8001,A12,Orders!$E$2:$E$8001,"Returned") -> 21768.63 | E12: =IFERROR(maxifs(Orders!$C$2:$C$8001,Orders!$B$2:$B$8001,A12),"") | F12: =IF(E12="","",MAX(Orders!$C$2:$C$8001)-E12) | G12: =IFERROR(CEILING(percentrank.inc($C$5:$C$604,C12)*4,1),1) -> 1 | H12: =IFERROR(CEILING(percentrank.inc($D$5:$D$604,D12)*4,1),1) -> 1 | I12: =IF(F12="",1,IFERROR(5-CEILING(percentrank.inc($F$5:$F$604,F12)*4,1),1)) -> 1 | J12: =IF(AND(I12>=3,G12>=3,H12>=3),"Champions",IF(AND(I12>=3,G12<=2),"New / Promising",IF(AND(I12<=2,G12>=3,H12>=3),"At Risk (High Value)",IF(AND(I12<=2,G12<=2),"Lost / Dormant","Regular")))) -> Lost / Dormant
A13: =Customers!A10 -> CUST00009 | B13: =Customers!B10&" "&Customers!C10 -> Mia Rodriguez | C13: =COUNTIFS(Orders!$B$2:$B$8001,A13,Orders!$E$2:$E$8001,"Delivered")+COUNTIFS(Orders!$B$2:$B$8001,A13,Orders!$E$2:$E$8001,"Returned") -> 4 | D13: =SUMIFS(Orders!$H$2:$H$8001,Orders!$B$2:$B$8001,A13,Orders!$E$2:$E$8001,"Delivered")+SUMIFS(Orders!$H$2:$H$8001,Orders!$B$2:$B$8001,A13,Orders!$E$2:$E$8001,"Returned") -> 22723.15 | E13: =IFERROR(maxifs(Orders!$C$2:$C$8001,Orders!$B$2:$B$8001,A13),"") | F13: =IF(E13="","",MAX(Orders!$C$2:$C$8001)-E13) | G13: =IFERROR(CEILING(percentrank.inc($C$5:$C$604,C13)*4,1),1) -> 1 | H13: =IFERROR(CEILING(percentrank.inc($D$5:$D$604,D13)*4,1),1) -> 1 | I13: =IF(F13="",1,IFERROR(5-CEILING(percentrank.inc($F$5:$F$604,F13)*4,1),1)) -> 1 | J13: =IF(AND(I13>=3,G13>=3,H13>=3),"Champions",IF(AND(I13>=3,G13<=2),"New / Promising",IF(AND(I13<=2,G13>=3,H13>=3),"At Risk (High Value)",IF(AND(I13<=2,G13<=2),"Lost / Dormant","Regular")))) -> Lost / Dormant
A14: =Customers!A11 -> CUST00010 | B14: =Customers!B11&" "&Customers!C11 -> Liam Thomas | C14: =COUNTIFS(Orders!$B$2:$B$8001,A14,Orders!$E$2:$E$8001,"Delivered")+COUNTIFS(Orders!$B$2:$B$8001,A14,Orders!$E$2:$E$8001,"Returned") -> 33 | D14: =SUMIFS(Orders!$H$2:$H$8001,Orders!$B$2:$B$8001,A14,Orders!$E$2:$E$8001,"Delivered")+SUMIFS(Orders!$H$2:$H$8001,Orders!$B$2:$B$8001,A14,Orders!$E$2:$E$8001,"Returned") -> 257174.11 | E14: =IFERROR(maxifs(Orders!$C$2:$C$8001,Orders!$B$2:$B$8001,A14),"") | F14: =IF(E14="","",MAX(Orders!$C$2:$C$8001)-E14) | G14: =IFERROR(CEILING(percentrank.inc($C$5:$C$604,C14)*4,1),1) -> 1 | H14: =IFERROR(CEILING(percentrank.inc($D$5:$D$604,D14)*4,1),1) -> 1 | I14: =IF(F14="",1,IFERROR(5-CEILING(percentrank.inc($F$5:$F$604,F14)*4,1),1)) -> 1 | J14: =IF(AND(I14>=3,G14>=3,H14>=3),"Champions",IF(AND(I14>=3,G14<=2),"New / Promising",IF(AND(I14<=2,G14>=3,H14>=3),"At Risk (High Value)",IF(AND(I14<=2,G14<=2),"Lost / Dormant","Regular")))) -> Lost / Dormant
A15: =Customers!A12 -> CUST00011 | B15: =Customers!B12&" "&Customers!C12 -> Diego Singh | C15: =COUNTIFS(Orders!$B$2:$B$8001,A15,Orders!$E$2:$E$8001,"Delivered")+COUNTIFS(Orders!$B$2:$B$8001,A15,Orders!$E$2:$E$8001,"Returned") -> 7 | D15: =SUMIFS(Orders!$H$2:$H$8001,Orders!$B$2:$B$8001,A15,Orders!$E$2:$E$8001,"Delivered")+SUMIFS(Orders!$H$2:$H$8001,Orders!$B$2:$B$8001,A15,Orders!$E$2:$E$8001,"Returned") -> 16749.97 | E15: =IFERROR(maxifs(Orders!$C$2:$C$8001,Orders!$B$2:$B$8001,A15),"") | F15: =IF(E15="","",MAX(Orders!$C$2:$C$8001)-E15) | G15: =IFERROR(CEILING(percentrank.inc($C$5:$C$604,C15)*4,1),1) -> 1 | H15: =IFERROR(CEILING(percentrank.inc($D$5:$D$604,D15)*4,1),1) -> 1 | I15: =IF(F15="",1,IFERROR(5-CEILING(percentrank.inc($F$5:$F$604,F15)*4,1),1)) -> 1 | J15: =IF(AND(I15>=3,G15>=3,H15>=3),"Champions",IF(AND(I15>=3,G15<=2),"New / Promising",IF(AND(I15<=2,G15>=3,H15>=3),"At Risk (High Value)",IF(AND(I15<=2,G15<=2),"Lost / Dormant","Regular")))) -> Lost / Dormant
A16: =Customers!A13 -> CUST00012 | B16: =Customers!B13&" "&Customers!C13 -> William Davis | C16: =COUNTIFS(Orders!$B$2:$B$8001,A16,Orders!$E$2:$E$8001,"Delivered")+COUNTIFS(Orders!$B$2:$B$8001,A16,Orders!$E$2:$E$8001,"Returned") -> 6 | D16: =SUMIFS(Orders!$H$2:$H$8001,Orders!$B$2:$B$8001,A16,Orders!$E$2:$E$8001,"Delivered")+SUMIFS(Orders!$H$2:$H$8001,Orders!$B$2:$B$8001,A16,Orders!$E$2:$E$8001,"Returned") -> 31400.26 | E16: =IFERROR(maxifs(Orders!$C$2:$C$8001,Orders!$B$2:$B$8001,A16),"") | F16: =IF(E16="","",MAX(Orders!$C$2:$C$8001)-E16) | G16: =IFERROR(CEILING(percentrank.inc($C$5:$C$604,C16)*4,1),1) -> 1 | H16: =IFERROR(CEILING(percentrank.inc($D$5:$D$604,D16)*4,1),1) -> 1 | I16: =IF(F16="",1,IFERROR(5-CEILING(percentrank.inc($F$5:$F$604,F16)*4,1),1)) -> 1 | J16: =IF(AND(I16>=3,G16>=3,H16>=3),"Champions",IF(AND(I16>=3,G16<=2),"New / Promising",IF(AND(I16<=2,G16>=3,H16>=3),"At Risk (High Value)",IF(AND(I16<=2,G16<=2),"Lost / Dormant","Regular")))) -> Lost / Dormant
A17: =Customers!A14 -> CUST00013 | B17: =Customers!B14&" "&Customers!C14 -> Aditya Wilson | C17: =COUNTIFS(Orders!$B$2:$B$8001,A17,Orders!$E$2:$E$8001,"Delivered")+COUNTIFS(Orders!$B$2:$B$8001,A17,Orders!$E$2:$E$8001,"Returned") -> 4 | D17: =SUMIFS(Orders!$H$2:$H$8001,Orders!$B$2:$B$8001,A17,Orders!$E$2:$E$8001,"Delivered")+SUMIFS(Orders!$H$2:$H$8001,Orders!$B$2:$B$8001,A17,Orders!$E$2:$E$8001,"Returned") -> 14325.8 | E17: =IFERROR(maxifs(Orders!$C$2:$C$8001,Orders!$B$2:$B$8001,A17),"") | F17: =IF(E17="","",MAX(Orders!$C$2:$C$8001)-E17) | G17: =IFERROR(CEILING(percentrank.inc($C$5:$C$604,C17)*4,1),1) -> 1 | H17: =IFERROR(CEILING(percentrank.inc($D$5:$D$604,D17)*4,1),1) -> 1 | I17: =IF(F17="",1,IFERROR(5-CEILING(percentrank.inc($F$5:$F$604,F17)*4,1),1)) -> 1 | J17: =IF(AND(I17>=3,G17>=3,H17>=3),"Champions",IF(AND(I17>=3,G17<=2),"New / Promising",IF(AND(I17<=2,G17>=3,H17>=3),"At Risk (High Value)",IF(AND(I17<=2,G17<=2),"Lost / Dormant","Regular")))) -> Lost / Dormant
A18: =Customers!A15 -> CUST00014 | B18: =Customers!B15&" "&Customers!C15 -> James Brown | C18: =COUNTIFS(Orders!$B$2:$B$8001,A18,Orders!$E$2:$E$8001,"Delivered")+COUNTIFS(Orders!$B$2:$B$8001,A18,Orders!$E$2:$E$8001,"Returned") -> 39 | D18: =SUMIFS(Orders!$H$2:$H$8001,Orders!$B$2:$B$8001,A18,Orders!$E$2:$E$8001,"Delivered")+SUMIFS(Orders!$H$2:$H$8001,Orders!$B$2:$B$8001,A18,Orders!$E$2:$E$8001,"Returned") -> 300107.66 | E18: =IFERROR(maxifs(Orders!$C$2:$C$8001,Orders!$B$2:$B$8001,A18),"") | F18: =IF(E18="","",MAX(Orders!$C$2:$C$8001)-E18) | G18: =IFERROR(CEILING(percentrank.inc($C$5:$C$604,C18)*4,1),1) -> 1 | H18: =IFERROR(CEILING(percentrank.inc($D$5:$D$604,D18)*4,1),1) -> 1 | I18: =IF(F18="",1,IFERROR(5-CEILING(percentrank.inc($F$5:$F$604,F18)*4,1),1)) -> 1 | J18: =IF(AND(I18>=3,G18>=3,H18>=3),"Champions",IF(AND(I18>=3,G18<=2),"New / Promising",IF(AND(I18<=2,G18>=3,H18>=3),"At Risk (High Value)",IF(AND(I18<=2,G18<=2),"Lost / Dormant","Regular")))) -> Lost / Dormant
A19: =Customers!A16 -> CUST00015 | B19: =Customers!B16&" "&Customers!C16 -> Anika Iyer | C19: =COUNTIFS(Orders!$B$2:$B$8001,A19,Orders!$E$2:$E$8001,"Delivered")+COUNTIFS(Orders!$B$2:$B$8001,A19,Orders!$E$2:$E$8001,"Returned") -> 3 | D19: =SUMIFS(Orders!$H$2:$H$8001,Orders!$B$2:$B$8001,A19,Orders!$E$2:$E$8001,"Delivered")+SUMIFS(Orders!$H$2:$H$8001,Orders!$B$2:$B$8001,A19,Orders!$E$2:$E$8001,"Returned") -> 11875.52 | E19: =IFERROR(maxifs(Orders!$C$2:$C$8001,Orders!$B$2:$B$8001,A19),"") | F19: =IF(E19="","",MAX(Orders!$C$2:$C$8001)-E19) | G19: =IFERROR(CEILING(percentrank.inc($C$5:$C$604,C19)*4,1),1) -> 1 | H19: =IFERROR(CEILING(percentrank.inc($D$5:$D$604,D19)*4,1),1) -> 1 | I19: =IF(F19="",1,IFERROR(5-CEILING(percentrank.inc($F$5:$F$604,F19)*4,1),1)) -> 1 | J19: =IF(AND(I19>=3,G19>=3,H19>=3),"Champions",IF(AND(I19>=3,G19<=2),"New / Promising",IF(AND(I19<=2,G19>=3,H19>=3),"At Risk (High Value)",IF(AND(I19<=2,G19<=2),"Lost / Dormant","Regular")))) -> Lost / Dormant
A20: =Customers!A17 -> CUST00016 | B20: =Customers!B17&" "&Customers!C17 -> David Thomas | C20: =COUNTIFS(Orders!$B$2:$B$8001,A20,Orders!$E$2:$E$8001,"Delivered")+COUNTIFS(Orders!$B$2:$B$8001,A20,Orders!$E$2:$E$8001,"Returned") -> 10 | D20: =SUMIFS(Orders!$H$2:$H$8001,Orders!$B$2:$B$8001,A20,Orders!$E$2:$E$8001,"Delivered")+SUMIFS(Orders!$H$2:$H$8001,Orders!$B$2:$B$8001,A20,Orders!$E$2:$E$8001,"Returned") -> 79846.94 | E20: =IFERROR(maxifs(Orders!$C$2:$C$8001,Orders!$B$2:$B$8001,A20),"") | F20: =IF(E20="","",MAX(Orders!$C$2:$C$8001)-E20) | G20: =IFERROR(CEILING(percentrank.inc($C$5:$C$604,C20)*4,1),1) -> 1 | H20: =IFERROR(CEILING(percentrank.inc($D$5:$D$604,D20)*4,1),1) -> 1 | I20: =IF(F20="",1,IFERROR(5-CEILING(percentrank.inc($F$5:$F$604,F20)*4,1),1)) -> 1 | J20: =IF(AND(I20>=3,G20>=3,H20>=3),"Champions",IF(AND(I20>=3,G20<=2),"New / Promising",IF(AND(I20<=2,G20>=3,H20>=3),"At Risk (High Value)",IF(AND(I20<=2,G20<=2),"Lost / Dormant","Regular")))) -> Lost / Dormant
... A604: =Customers!A601 -> CUST00600 | B604: =Customers!B601&" "&Customers!C601 -> Aarav Wilson | C604: =COUNTIFS(Orders!$B$2:$B$8001,A604,Orders!$E$2:$E$8001,"Delivered")+COUNTIFS(Orders!$B$2:$B$8001,A604,Orders!$E$2:$E$8001,"Returned") -> 18 | D604: =SUMIFS(Orders!$H$2:$H$8001,Orders!$B$2:$B$8001,A604,Orders!$E$2:$E$8001,"Delivered")+SUMIFS(Orders!$H$2:$H$8001,Orders!$B$2:$B$8001,A604,Orders!$E$2:$E$8001,"Returned") -> 94338.22 | E604: =IFERROR(maxifs(Orders!$C$2:$C$8001,Orders!$B$2:$B$8001,A604),"") | F604: =IF(E604="","",MAX(Orders!$C$2:$C$8001)-E604) | G604: =IFERROR(CEILING(percentrank.inc($C$5:$C$604,C604)*4,1),1) -> 1 | H604: =IFERROR(CEILING(percentrank.inc($D$5:$D$604,D604)*4,1),1) -> 1 | I604: =IF(F604="",1,IFERROR(5-CEILING(percentrank.inc($F$5:$F$604,F604)*4,1),1)) -> 1 | J604: =IF(AND(I604>=3,G604>=3,H604>=3),"Champions",IF(AND(I604>=3,G604<=2),"New / Promising",IF(AND(I604<=2,G604>=3,H604>=3),"At Risk (High Value)",IF(AND(I604<=2,G604<=2),"Lost / Dormant","Regular")))) -> Lost / Dormant

Sheet Returns_Analysis
A1: Product Returns Analysis
A3: Return Reason | B3: Count | C3: % of Returns | D3: Refund Value
A4: Better Price Found Elsewhere | B4: =COUNTIF(Returns!$G$2:$G$884,A4) -> 136 | C4: =B4/SUM($B$4:$B$10) -> 0.15402039 | D4: =SUMIF(Returns!$G$2:$G$884,A4,Returns!$H$2:$H$884) -> 380832.96
A5: Changed Mind | B5: =COUNTIF(Returns!$G$2:$G$884,A5) -> 131 | C5: =B5/SUM($B$4:$B$10) -> 0.14835787 | D5: =SUMIF(Returns!$G$2:$G$884,A5,Returns!$H$2:$H$884) -> 339296.47
A6: Not as Described | B6: =COUNTIF(Returns!$G$2:$G$884,A6) -> 119 | C6: =B6/SUM($B$4:$B$10) -> 0.13476784 | D6: =SUMIF(Returns!$G$2:$G$884,A6,Returns!$H$2:$H$884) -> 298701.34
A7: Product Damaged | B7: =COUNTIF(Returns!$G$2:$G$884,A7) -> 116 | C7: =B7/SUM($B$4:$B$10) -> 0.13137033 | D7: =SUMIF(Returns!$G$2:$G$884,A7,Returns!$H$2:$H$884) -> 272768.48
A8: Quality Issue | B8: =COUNTIF(Returns!$G$2:$G$884,A8) -> 123 | C8: =B8/SUM($B$4:$B$10) -> 0.13929785 | D8: =SUMIF(Returns!$G$2:$G$884,A8,Returns!$H$2:$H$884) -> 348987.89
A9: Size/Fit Issue | B9: =COUNTIF(Returns!$G$2:$G$884,A9) -> 126 | C9: =B9/SUM($B$4:$B$10) -> 0.14269536 | D9: =SUMIF(Returns!$G$2:$G$884,A9,Returns!$H$2:$H$884) -> 306833
A10: Wrong Item Delivered | B10: =COUNTIF(Returns!$G$2:$G$884,A10) -> 132 | C10: =B10/SUM($B$4:$B$10) -> 0.14949037 | D10: =SUMIF(Returns!$G$2:$G$884,A10,Returns!$H$2:$H$884) -> 342335.28
A13: Top 10 Most-Returned Products
A14: Product Name | B14: Category | C14: Times Returned | D14: Total Refunded
A15: Kids Activity Book | B15: Books & Stationery | C15: =SUMPRODUCT((IFERROR(INDEX(Products!$B$2:$B$51,MATCH(Returns!$D$2:$D$884,Products!$A$2:$A$51,0)),"")=A15)*1) -> 139 | D15: =SUMPRODUCT((IFERROR(INDEX(Products!$B$2:$B$51,MATCH(Returns!$D$2:$D$884,Products!$A$2:$A$51,0)),"")=A15)*Returns!$H$2:$H$884) -> 82113.48
A16: Gaming Mouse | B16: Electronics | C16: =SUMPRODUCT((IFERROR(INDEX(Products!$B$2:$B$51,MATCH(Returns!$D$2:$D$884,Products!$A$2:$A$51,0)),"")=A16)*1) -> 92 | D16: =SUMPRODUCT((IFERROR(INDEX(Products!$B$2:$B$51,MATCH(Returns!$D$2:$D$884,Products!$A$2:$A$51,0)),"")=A16)*Returns!$H$2:$H$884) -> 280127.31
A17: Denim Jeans | B17: Fashion | C17: =SUMPRODUCT((IFERROR(INDEX(Products!$B$2:$B$51,MATCH(Returns!$D$2:$D$884,Products!$A$2:$A$51,0)),"")=A17)*1) -> 77 | D17: =SUMPRODUCT((IFERROR(INDEX(Products!$B$2:$B$51,MATCH(Returns!$D$2:$D$884,Products!$A$2:$A$51,0)),"")=A17)*Returns!$H$2:$H$884) -> 214894.04
A18: Desk Organizer | B18: Books & Stationery | C18: =SUMPRODUCT((IFERROR(INDEX(Products!$B$2:$B$51,MATCH(Returns!$D$2:$D$884,Products!$A$2:$A$51,0)),"")=A18)*1) -> 70 | D18: =SUMPRODUCT((IFERROR(INDEX(Products!$B$2:$B$51,MATCH(Returns!$D$2:$D$884,Products!$A$2:$A$51,0)),"")=A18)*Returns!$H$2:$H$884) -> 71350.75
A19: Skipping Rope | B19: Sports & Fitness | C19: =SUMPRODUCT((IFERROR(INDEX(Products!$B$2:$B$51,MATCH(Returns!$D$2:$D$884,Products!$A$2:$A$51,0)),"")=A19)*1) -> 52 | D19: =SUMPRODUCT((IFERROR(INDEX(Products!$B$2:$B$51,MATCH(Returns!$D$2:$D$884,Products!$A$2:$A$51,0)),"")=A19)*Returns!$H$2:$H$884) -> 22822.79
A20: Adjustable Dumbbells | B20: Sports & Fitness | C20: =SUMPRODUCT((IFERROR(INDEX(Products!$B$2:$B$51,MATCH(Returns!$D$2:$D$884,Products!$A$2:$A$51,0)),"")=A20)*1) -> 47 | D20: =SUMPRODUCT((IFERROR(INDEX(Products!$B$2:$B$51,MATCH(Returns!$D$2:$D$884,Products!$A$2:$A$51,0)),"")=A20)*Returns!$H$2:$H$884) -> 326911.73
A21: Face Serum | B21: Beauty & Personal Care | C21: =SUMPRODUCT((IFERROR(INDEX(Products!$B$2:$B$51,MATCH(Returns!$D$2:$D$884,Products!$A$2:$A$51,0)),"")=A21)*1) -> 36 | D21: =SUMPRODUCT((IFERROR(INDEX(Products!$B$2:$B$51,MATCH(Returns!$D$2:$D$884,Products!$A$2:$A$51,0)),"")=A21)*Returns!$H$2:$H$884) -> 41509.79
A22: Hair Dryer | B22: Beauty & Personal Care | C22: =SUMPRODUCT((IFERROR(INDEX(Products!$B$2:$B$51,MATCH(Returns!$D$2:$D$884,Products!$A$2:$A$51,0)),"")=A22)*1) -> 27 | D22: =SUMPRODUCT((IFERROR(INDEX(Products!$B$2:$B$51,MATCH(Returns!$D$2:$D$884,Products!$A$2:$A$51,0)),"")=A22)*Returns!$H$2:$H$884) -> 56598.27
A23: Men's Casual Shirt | B23: Fashion | C23: =SUMPRODUCT((IFERROR(INDEX(Products!$B$2:$B$51,MATCH(Returns!$D$2:$D$884,Products!$A$2:$A$51,0)),"")=A23)*1) -> 25 | D23: =SUMPRODUCT((IFERROR(INDEX(Products!$B$2:$B$51,MATCH(Returns!$D$2:$D$884,Products!$A$2:$A$51,0)),"")=A23)*Returns!$H$2:$H$884) -> 49130.99
A24: Sunscreen SPF50 | B24: Beauty & Personal Care | C24: =SUMPRODUCT((IFERROR(INDEX(Products!$B$2:$B$51,MATCH(Returns!$D$2:$D$884,Products!$A$2:$A$51,0)),"")=A24)*1) -> 23 | D24: =SUMPRODUCT((IFERROR(INDEX(Products!$B$2:$B$51,MATCH(Returns!$D$2:$D$884,Products!$A$2:$A$51,0)),"")=A24)*Returns!$H$2:$H$884) -> 16073.4
A27: Overall Return Rate | B27: =COUNTA(Returns!A2:A884)/COUNTA(Orders!A2:A8001) -> 0.110375

Sheet Customers
A1: customer_id | B1: first_name | C1: last_name | D1: email | E1: city | F1: country | G1: region | H1: signup_date | I1: acquisition_channel | J1: age | K1: gender | L1: membership_tier
A2: CUST00001 | B2: Liam | C2: Nair | D2: liam.nair1@example.com | E2: Mumbai | F2: India | G2: APAC | H2: 2024-07-17 | I2: Paid Search | J2: 38 | K2: Male | L2: Silver
A3: CUST00002 | B3: Lucas | C3: Ramirez | D3: lucas.ramirez2@example.com | E3: Bengaluru | F3: India | G3: APAC | H3: 2025-05-14 | I3: Organic Search | J3: 32 | K3: Male | L3: Standard
A4: CUST00003 | B4: Elizabeth | C4: Young | D4: elizabeth.young3@example.com | E4: Mumbai | F4: India | G4: APAC | H4: 2024-02-12 | I4: Email Marketing | J4: 39 | K4: Other | L4: Silver
A5: CUST00004 | B5: Kiara | C5: Perez | D5: kiara.perez4@example.com | E5: Toronto | F5: Canada | G5: North America | H5: 2024-07-23 | I5: Referral | J5: 47 | K5: Male | L5: Silver
A6: CUST00005 | B6: Ananya | C6: Lee | D6: ananya.lee5@example.com | E6: New York | F6: USA | G6: North America | H6: 2024-07-23 | I6: Organic Search | J6: 31 | K6: Female | L6: Standard
A7: CUST00006 | B7: William | C7: Reddy | D7: william.reddy6@example.com | E7: Los Angeles | F7: USA | G7: North America | H7: 2024-12-05 | I7: Email Marketing | J7: 31 | K7: Male | L7: Silver
A8: CUST00007 | B8: Susan | C8: Nair | D8: susan.nair7@example.com | E8: Chicago | F8: USA | G8: North America | H8: 2023-06-11 | I8: Social Media | J8: 48 | K8: Other | L8: Silver
A9: CUST00008 | B9: Sofia | C9: Thomas | D9: sofia.thomas8@example.com | E9: Toronto | F9: Canada | G9: North America | H9: 2024-01-29 | I9: Email Marketing | J9: 40 | K9: Male | L9: Silver
A10: CUST00009 | B10: Mia | C10: Rodriguez | D10: mia.rodriguez9@example.com | E10: Bengaluru | F10: India | G10: APAC | H10: 2024-04-21 | I10: Direct | J10: 29 | K10: Female | L10: Standard
A11: CUST00010 | B11: Liam | C11: Thomas | D11: liam.thomas10@example.com | E11: Pune | F11: India | G11: APAC | H11: 2025-01-28 | I11: Paid Search | J11: 38 | K11: Other | L11: Standard
A12: CUST00011 | B12: Diego | C12: Singh | D12: diego.singh11@example.com | E12: Vancouver | F12: Canada | G12: North America | H12: 2023-12-17 | I12: Social Media | J12: 29 | K12: Male | L12: Standard
A13: CUST00012 | B13: William | C13: Davis | D13: william.davis12@example.com | E13: Sydney | F13: Australia | G13: APAC | H13: 2024-03-25 | I13: Email Marketing | J13: 29 | K13: Male | L13: Standard
... A601: CUST00600 | B601: Aarav | C601: Wilson | D601: aarav.wilson600@example.com | E601: Singapore | F601: Singapore | G601: APAC | H601: 2024-01-26 | I601: Organic Search | J601: 37 | K601: Male | L601: Silver

Sheet Products
A1: product_id | B1: product_name | C1: category | D1: unit_cost | E1: unit_price | F1: margin_pct
A2: PROD0001 | B2: Wireless Earbuds | C2: Electronics | D2: 1222.65 | E2: 2978.99 | F2: 0.59
A3: PROD0002 | B3: Smartwatch | C3: Electronics | D3: 3061.35 | E3: 4273.58 | F3: 0.284
A4: PROD0003 | B4: Bluetooth Speaker | C4: Electronics | D4: 1356.14 | E4: 3142.61 | F4: 0.568
A5: PROD0004 | B5: Laptop Backpack | C5: Electronics | D5: 614.42 | E5: 1971 | F5: 0.688
A6: PROD0005 | B6: Power Bank 20000mAh | C6: Electronics | D6: 818.21 | E6: 1478.08 | F6: 0.446
A7: PROD0006 | B7: Smartphone Case | C7: Electronics | D7: 405.18 | E7: 657.82 | F7: 0.384
A8: PROD0007 | B8: Gaming Mouse | C8: Electronics | D8: 774.46 | E8: 2398.35 | F8: 0.677
A9: PROD0008 | B9: USB-C Hub | C9: Electronics | D9: 1042.01 | E9: 1111.28 | F9: 0.062
A10: PROD0009 | B10: Noise Cancelling Headphones | C10: Electronics | D10: 6193.21 | E10: 7194.38 | F10: 0.139
A11: PROD0010 | B11: Action Camera | C11: Electronics | D11: 4455.89 | E11: 14558.72 | F11: 0.694
A12: PROD0011 | B12: Men's Casual Shirt | C12: Fashion | D12: 1147.02 | E12: 1364.75 | F12: 0.16
A13: PROD0012 | B13: Women's Kurti | C13: Fashion | D13: 535.76 | E13: 1572.6 | F13: 0.659
... A51: PROD0050 | B51: Desk Organizer | C51: Books & Stationery | D51: 340.65 | E51: 750.27 | F51: 0.546

Sheet Orders
A1: order_id | B1: customer_id | C1: order_date | D1: payment_method | E1: order_status | F1: shipping_fee | G1: order_subtotal | H1: total_amount
A2: ORD000001 | B2: CUST00573 | C2: 2024-02-26 | D2: UPI | E2: Delivered | F2: 79 | G2: 2459.37 | H2: 2538.37
A3: ORD000002 | B3: CUST00083 | C3: 2025-06-05 | D3: Debit Card | E3: Cancelled | F3: 0 | G3: 2501.08 | H3: 2501.08
A4: ORD000003 | B4: CUST00408 | C4: 2024-09-13 | D4: Credit Card | E4: Delivered | F4: 0 | G4: 14836.35 | H4: 14836.35
A5: ORD000004 | B5: CUST00531 | C5: 2025-04-24 | D5: Wallet | E5: Delivered | F5: 99 | G5: 2374.12 | H5: 2473.12
A6: ORD000005 | B6: CUST00401 | C6: 2024-07-08 | D6: UPI | E6: Delivered | F6: 0 | G6: 5045.75 | H6: 5045.75
A7: ORD000006 | B7: CUST00600 | C7: 2025-05-29 | D7: Net Banking | E7: Delivered | F7: 99 | G7: 712.76 | H7: 811.76
A8: ORD000007 | B8: CUST00463 | C8: 2025-11-01 | D8: Wallet | E8: Delivered | F8: 79 | G8: 1569.42 | H8: 1648.42
A9: ORD000008 | B9: CUST00481 | C9: 2025-07-20 | D9: UPI | E9: Delivered | F9: 0 | G9: 11980.17 | H9: 11980.17
A10: ORD000009 | B10: CUST00265 | C10: 2024-10-29 | D10: Net Banking | E10: Delivered | F10: 0 | G10: 3791.32 | H10: 3791.32
A11: ORD000010 | B11: CUST00040 | C11: 2024-07-16 | D11: Wallet | E11: Delivered | F11: 0 | G11: 7426.39 | H11: 7426.39
A12: ORD000011 | B12: CUST00320 | C12: 2025-10-28 | D12: Debit Card | E12: Delivered | F12: 0 | G12: 7496.76 | H12: 7496.76
A13: ORD000012 | B13: CUST00328 | C13: 2025-03-21 | D13: UPI | E13: Delivered | F13: 0 | G13: 6154.37 | H13: 6154.37
... A8001: ORD008000 | B8001: CUST00420 | C8001: 2024-10-09 | D8001: Cash on Delivery | E8001: Delivered | F8001: 0 | G8001: 15050.02 | H8001: 15050.02

Sheet Order_Items
A1: order_item_id | B1: order_id | C1: product_id | D1: quantity | E1: unit_price | F1: discount_pct | G1: line_total | I1: category | J1: order_status | K1: order_month
A2: OI000001 | B2: ORD000001 | C2: PROD0049 | D2: 1 | E2: 482.17 | F2: 0.2 | G2: 385.74 | I2: =INDEX(Products!$C$2:$C$51,MATCH(C2,Products!$A$2:$A$51,0)) -> Books & Stationery | J2: =INDEX(Orders!$E$2:$E$8001,MATCH(B2,Orders!$A$2:$A$8001,0)) -> Delivered | K2: =LEFT(INDEX(Orders!$C$2:$C$8001,MATCH(B2,Orders!$A$2:$A$8001,0)),7) -> 2024-02
A3: OI000002 | B3: ORD000001 | C3: PROD0029 | D3: 1 | E3: 2073.63 | F3: 0 | G3: 2073.63 | I3: =INDEX(Products!$C$2:$C$51,MATCH(C3,Products!$A$2:$A$51,0)) -> Home & Kitchen | J3: =INDEX(Orders!$E$2:$E$8001,MATCH(B3,Orders!$A$2:$A$8001,0)) -> Delivered | K3: =LEFT(INDEX(Orders!$C$2:$C$8001,MATCH(B3,Orders!$A$2:$A$8001,0)),7) -> 2024-02
A4: OI000003 | B4: ORD000002 | C4: PROD0015 | D4: 2 | E4: 1250.54 | F4: 0 | G4: 2501.08 | I4: =INDEX(Products!$C$2:$C$51,MATCH(C4,Products!$A$2:$A$51,0)) -> Fashion | J4: =INDEX(Orders!$E$2:$E$8001,MATCH(B4,Orders!$A$2:$A$8001,0)) -> Cancelled | K4: =LEFT(INDEX(Orders!$C$2:$C$8001,MATCH(B4,Orders!$A$2:$A$8001,0)),7) -> 2025-06
A5: OI000004 | B5: ORD000003 | C5: PROD0007 | D5: 1 | E5: 2398.35 | F5: 0.15 | G5: 2038.6 | I5: =INDEX(Products!$C$2:$C$51,MATCH(C5,Products!$A$2:$A$51,0)) -> Electronics | J5: =INDEX(Orders!$E$2:$E$8001,MATCH(B5,Orders!$A$2:$A$8001,0)) -> Delivered | K5: =LEFT(INDEX(Orders!$C$2:$C$8001,MATCH(B5,Orders!$A$2:$A$8001,0)),7) -> 2024-09
A6: OI000005 | B6: ORD000003 | C6: PROD0043 | D6: 2 | E6: 2914.27 | F6: 0.1 | G6: 5245.69 | I6: =INDEX(Products!$C$2:$C$51,MATCH(C6,Products!$A$2:$A$51,0)) -> Sports & Fitness | J6: =INDEX(Orders!$E$2:$E$8001,MATCH(B6,Orders!$A$2:$A$8001,0)) -> Delivered | K6: =LEFT(INDEX(Orders!$C$2:$C$8001,MATCH(B6,Orders!$A$2:$A$8001,0)),7) -> 2024-09
A7: OI000006 | B7: ORD000003 | C7: PROD0029 | D7: 3 | E7: 2073.63 | F7: 0.05 | G7: 5909.85 | I7: =INDEX(Products!$C$2:$C$51,MATCH(C7,Products!$A$2:$A$51,0)) -> Home & Kitchen | J7: =INDEX(Orders!$E$2:$E$8001,MATCH(B7,Orders!$A$2:$A$8001,0)) -> Delivered | K7: =LEFT(INDEX(Orders!$C$2:$C$8001,MATCH(B7,Orders!$A$2:$A$8001,0)),7) -> 2024-09
A8: OI000007 | B8: ORD000003 | C8: PROD0049 | D8: 1 | E8: 482.17 | F8: 0 | G8: 482.17 | I8: =INDEX(Products!$C$2:$C$51,MATCH(C8,Products!$A$2:$A$51,0)) -> Books & Stationery | J8: =INDEX(Orders!$E$2:$E$8001,MATCH(B8,Orders!$A$2:$A$8001,0)) -> Delivered | K8: =LEFT(INDEX(Orders!$C$2:$C$8001,MATCH(B8,Orders!$A$2:$A$8001,0)),7) -> 2024-09
A9: OI000008 | B9: ORD000003 | C9: PROD0011 | D9: 1 | E9: 1364.75 | F9: 0.15 | G9: 1160.04 | I9: =INDEX(Products!$C$2:$C$51,MATCH(C9,Products!$A$2:$A$51,0)) -> Fashion | J9: =INDEX(Orders!$E$2:$E$8001,MATCH(B9,Orders!$A$2:$A$8001,0)) -> Delivered | K9: =LEFT(INDEX(Orders!$C$2:$C$8001,MATCH(B9,Orders!$A$2:$A$8001,0)),7) -> 2024-09
A10: OI000009 | B10: ORD000004 | C10: PROD0004 | D10: 1 | E10: 1971 | F10: 0.1 | G10: 1773.9 | I10: =INDEX(Products!$C$2:$C$51,MATCH(C10,Products!$A$2:$A$51,0)) -> Electronics | J10: =INDEX(Orders!$E$2:$E$8001,MATCH(B10,Orders!$A$2:$A$8001,0)) -> Delivered | K10: =LEFT(INDEX(Orders!$C$2:$C$8001,MATCH(B10,Orders!$A$2:$A$8001,0)),7) -> 2025-04
A11: OI000010 | B11: ORD000004 | C11: PROD0050 | D11: 1 | E11: 750.27 | F11: 0.2 | G11: 600.22 | I11: =INDEX(Products!$C$2:$C$51,MATCH(C11,Products!$A$2:$A$51,0)) -> Books & Stationery | J11: =INDEX(Orders!$E$2:$E$8001,MATCH(B11,Orders!$A$2:$A$8001,0)) -> Delivered | K11: =LEFT(INDEX(Orders!$C$2:$C$8001,MATCH(B11,Orders!$A$2:$A$8001,0)),7) -> 2025-04
A12: OI000011 | B12: ORD000005 | C12: PROD0040 | D12: 1 | E12: 5311.32 | F12: 0.05 | G12: 5045.75 | I12: =INDEX(Products!$C$2:$C$51,MATCH(C12,Products!$A$2:$A$51,0)) -> Sports & Fitness | J12: =INDEX(Orders!$E$2:$E$8001,MATCH(B12,Orders!$A$2:$A$8001,0)) -> Delivered | K12: =LEFT(INDEX(Orders!$C$2:$C$8001,MATCH(B12,Orders!$A$2:$A$8001,0)),7) -> 2024-07
A13: OI000012 | B13: ORD000006 | C13: PROD0050 | D13: 1 | E13: 750.27 | F13: 0.05 | G13: 712.76 | I13: =INDEX(Products!$C$2:$C$51,MATCH(C13,Products!$A$2:$A$51,0)) -> Books & Stationery | J13: =INDEX(Orders!$E$2:$E$8001,MATCH(B13,Orders!$A$2:$A$8001,0)) -> Delivered | K13: =LEFT(INDEX(Orders!$C$2:$C$8001,MATCH(B13,Orders!$A$2:$A$8001,0)),7) -> 2025-05
... A16419: OI016418 | B16419: ORD008000 | C16419: PROD0050 | D16419: 3 | E16419: 750.27 | F16419: 0.1 | G16419: 2025.73 | I16419: =INDEX(Products!$C$2:$C$51,MATCH(C16419,Products!$A$2:$A$51,0)) -> Books & Stationery | J16419: =INDEX(Orders!$E$2:$E$8001,MATCH(B16419,Orders!$A$2:$A$8001,0)) -> Delivered | K16419: =LEFT(INDEX(Orders!$C$2:$C$8001,MATCH(B16419,Orders!$A$2:$A$8001,0)),7) -> 2024-10

Sheet Returns
A1: return_id | B1: order_id | C1: order_item_id | D1: product_id | E1: customer_id | F1: return_date | G1: return_reason | H1: refund_amount
A2: RET00001 | B2: ORD000014 | C2: OI000028 | D2: PROD0031 | E2: CUST00239 | F2: 2025-12-15 | G2: Not as Described | H2: 862.99
A3: RET00002 | B3: ORD000037 | C3: OI000073 | D3: PROD0049 | E3: CUST00496 | F3: 2025-05-19 | G3: Product Damaged | H3: 1446.51
A4: RET00003 | B4: ORD000038 | C4: OI000076 | D4: PROD0024 | E4: CUST00371 | F4: 2024-12-29 | G4: Changed Mind | H4: 3493.68
A5: RET00004 | B5: ORD000040 | C5: OI000082 | D5: PROD0049 | E5: CUST00094 | F5: 2025-06-06 | G5: Size/Fit Issue | H5: 482.17
A6: RET00005 | B6: ORD000054 | C6: OI000112 | D6: PROD0050 | E6: CUST00015 | F6: 2024-08-28 | G6: Better Price Found Elsewhere | H6: 600.22
A7: RET00006 | B7: ORD000063 | C7: OI000130 | D7: PROD0034 | E7: CUST00313 | F7: 2025-04-08 | G7: Size/Fit Issue | H7: 591.85
A8: RET00007 | B8: ORD000077 | C8: OI000160 | D8: PROD0049 | E8: CUST00507 | F8: 2025-11-04 | G8: Changed Mind | H8: 458.06
A9: RET00008 | B9: ORD000082 | C9: OI000168 | D9: PROD0007 | E9: CUST00036 | F9: 2025-09-06 | G9: Changed Mind | H9: 2398.35
A10: RET00009 | B10: ORD000094 | C10: OI000196 | D10: PROD0049 | E10: CUST00469 | F10: 2025-07-07 | G10: Quality Issue | H10: 964.34
A11: RET00010 | B11: ORD000095 | C11: OI000197 | D11: PROD0013 | E11: CUST00592 | F11: 2024-08-29 | G11: Not as Described | H11: 2374.52
A12: RET00011 | B12: ORD000107 | C12: OI000216 | D12: PROD0050 | E12: CUST00215 | F12: 2024-02-13 | G12: Product Damaged | H12: 1275.46
A13: RET00012 | B13: ORD000115 | C13: OI000235 | D13: PROD0049 | E13: CUST00323 | F13: 2025-10-31 | G13: Changed Mind | H13: 482.17
... A884: RET00883 | B884: ORD007999 | C884: OI016414 | D884: PROD0050 | E884: CUST00434 | F884: 2024-10-25 | G884: Product Damaged | H884: 1350.49
